arrayfifo/__init__.py
arrayfifo-0.0.3.dist-info/LICENSE.md
arrayfifo-0.0.3.dist-info/METADATA
arrayfifo-0.0.3.dist-info/WHEEL
arrayfifo-0.0.3.dist-info/top_level.txt
arrayfifo-0.0.3.dist-info/RECORD
