Metadata-Version: 2.1
Name: arrayfifo
Version: 0.0.3
Summary: Fast multiprocessing FIFO buffer (queue) for numpy arrays
Home-page: https://github.com/danionella/arrayfifo
Author: jlab.berlin
Author-email: 
License: MIT
Classifier: Intended Audience :: Developers
Classifier: License :: OSI Approved :: MIT License
Classifier: Programming Language :: Python :: 3.7
Classifier: Programming Language :: Python :: 3.8
Classifier: Programming Language :: Python :: 3.9
Classifier: Programming Language :: Python :: 3.10
Classifier: Programming Language :: Python :: 3.11
License-File: LICENSE.md
